odoo/addons/mail_show_follower/README.rst
odoo/addons/mail_show_follower/__init__.py
odoo/addons/mail_show_follower/__manifest__.py
odoo/addons/mail_show_follower/i18n/fr.po
odoo/addons/mail_show_follower/i18n/mail_show_follower.pot
odoo/addons/mail_show_follower/models/__init__.py
odoo/addons/mail_show_follower/models/mail_mail.py
odoo/addons/mail_show_follower/models/res_company.py
odoo/addons/mail_show_follower/models/res_config_settings.py
odoo/addons/mail_show_follower/models/res_users.py
odoo/addons/mail_show_follower/readme/CONFIGURE.rst
odoo/addons/mail_show_follower/readme/CONTRIBUTORS.rst
odoo/addons/mail_show_follower/readme/DESCRIPTION.rst
odoo/addons/mail_show_follower/readme/USAGE.rst
odoo/addons/mail_show_follower/static/description/icon.png
odoo/addons/mail_show_follower/static/description/index.html
odoo/addons/mail_show_follower/views/res_config_settings.xml
odoo/addons/mail_show_follower/views/res_users.xml
odoo14_addon_mail_show_follower-14.0.1.1.0.dist-info/METADATA
odoo14_addon_mail_show_follower-14.0.1.1.0.dist-info/WHEEL
odoo14_addon_mail_show_follower-14.0.1.1.0.dist-info/top_level.txt
odoo14_addon_mail_show_follower-14.0.1.1.0.dist-info/RECORD
